tf_validator/__init__.py
tf_validator-0.1.dist-info/METADATA
tf_validator-0.1.dist-info/WHEEL
tf_validator-0.1.dist-info/top_level.txt
tf_validator-0.1.dist-info/RECORD
